syncfreedom/__init__.py
syncfreedom/client.py
syncfreedom/session.py
syncfreedom-1.0.8.dist-info/LICENSE
syncfreedom-1.0.8.dist-info/METADATA
syncfreedom-1.0.8.dist-info/WHEEL
syncfreedom-1.0.8.dist-info/top_level.txt
syncfreedom-1.0.8.dist-info/RECORD
