Metadata-Version: 2.1
Name: syncfreedom
Version: 1.0.8
Summary: Initial Release
Home-page: https://github.com/selfjared1/syncfreedom-lib/releases/tag/0.1
Download-URL: https://github.com/selfjared1/syncfreedom-lib/archive/refs/tags/0.1.zip
Author: Jared Self
Author-email: jared@quickbooksgg.com
Project-URL: Bug Tracker, https://github.com/selfjared1/syncfreedom-lib/issues
Keywords: quickbooks online,quickbooks
Classifier: Programming Language :: Python :: 3
Classifier: License :: OSI Approved :: MIT License
Classifier: Operating System :: OS Independent
Requires-Python: >=3.8
License-File: LICENSE
Requires-Dist: python-quickbooks
